<?xml version="1.0" encoding="UTF-8"?><record_update table="sp_widget">
    <sp_widget action="INSERT_OR_UPDATE">
        <category>custom</category>
        <client_script><![CDATA[api.controller=function() {  /* widget controller */  var c = this;};]]></client_script>
        <controller_as>c</controller_as>
        <css>[type="date"] {&#13;
  background:#fff url(https://cdn1.iconfinder.com/data/icons/cc_mono_icon_set/blacks/16x16/calendar_2.png)  97% 50% no-repeat ;&#13;
}&#13;
[type="date"]::-webkit-inner-spin-button {&#13;
  display: none;&#13;
}&#13;
[type="date"]::-webkit-calendar-picker-indicator {&#13;
  opacity: 0;&#13;
}&#13;
&#13;
/* custom styles */&#13;
body {&#13;
  padding: 4em;&#13;
  background: #e5e5e5;&#13;
  font: 13px/1.4 Geneva, 'Lucida Sans', 'Lucida Grande', 'Lucida Sans Unicode', Verdana, sans-serif;&#13;
}&#13;
label {&#13;
  display: block;&#13;
}&#13;
input {&#13;
  border: 1px solid #c4c4c4;&#13;
  border-radius: 5px;&#13;
  background-color: #fff;&#13;
  padding: 3px 5px;&#13;
  box-shadow: inset 0 3px 6px rgba(0,0,0,0.1);&#13;
  width: 190px;&#13;
}&#13;
label{&#13;
	color: black;&#13;
}</css>
        <data_table>sp_instance</data_table>
        <demo_data/>
        <description/>
        <docs/>
        <field_list/>
        <has_preview>true</has_preview>
        <id>hrs_check_out</id>
        <internal>false</internal>
        <link><![CDATA[function link(scope, element, attrs, controller) {  }]]></link>
        <name>HRS Check Out</name>
        <option_schema/>
        <public>true</public>
        <roles/>
        <script><![CDATA[(function() {  /* populate the 'data' object */  /* e.g., data.table = $sp.getValue('table'); */})();]]></script>
        <servicenow>false</servicenow>
        <sys_class_name>sp_widget</sys_class_name>
        <sys_created_by>admin</sys_created_by>
        <sys_created_on>2022-12-12 10:02:38</sys_created_on>
        <sys_id>ba6ab61c2f7bd1100c1058492799b606</sys_id>
        <sys_mod_count>1</sys_mod_count>
        <sys_name>HRS Check Out</sys_name>
        <sys_package display_value="Hotel Reservation System" source="x_881199_hotel_res">2171b6dc2f3bd1100c1058492799b6f5</sys_package>
        <sys_policy/>
        <sys_scope display_value="Hotel Reservation System">2171b6dc2f3bd1100c1058492799b6f5</sys_scope>
        <sys_update_name>sp_widget_ba6ab61c2f7bd1100c1058492799b606</sys_update_name>
        <sys_updated_by>admin</sys_updated_by>
        <sys_updated_on>2022-12-12 10:02:56</sys_updated_on>
        <template><![CDATA[<div>
	<label for="checkout">Check-out</label><br>
	<input type="date" name="checkout" id="checkout">
</div>]]></template>
    </sp_widget>
</record_update>
