<?xml version="1.0" encoding="UTF-8"?><record_update>
    <sys_dictionary action="DELETE" element="age" table="x_881199_hotel_res_hrs_user_profile">
        <active>true</active>
        <array>false</array>
        <array_denormalized>false</array_denormalized>
        <attributes/>
        <audit>false</audit>
        <calculation/>
        <choice>0</choice>
        <choice_field/>
        <choice_table/>
        <column_label>Age</column_label>
        <comments/>
        <create_roles/>
        <default_value/>
        <defaultsort/>
        <delete_roles/>
        <dependent/>
        <dependent_on_field/>
        <display>false</display>
        <dynamic_creation>false</dynamic_creation>
        <dynamic_creation_script/>
        <dynamic_default_value/>
        <dynamic_ref_qual/>
        <element>age</element>
        <element_reference>false</element_reference>
        <foreign_database/>
        <function_definition/>
        <function_field>false</function_field>
        <internal_type display_value="Integer">integer</internal_type>
        <mandatory>false</mandatory>
        <max_length>40</max_length>
        <name>x_881199_hotel_res_hrs_user_profile</name>
        <next_element/>
        <primary>false</primary>
        <read_only>false</read_only>
        <read_roles/>
        <reference/>
        <reference_cascade_rule/>
        <reference_floats>false</reference_floats>
        <reference_key/>
        <reference_qual/>
        <reference_qual_condition/>
        <reference_type/>
        <sizeclass/>
        <spell_check>false</spell_check>
        <staged>false</staged>
        <sys_class_name>sys_dictionary</sys_class_name>
        <sys_created_by>miguel.b</sys_created_by>
        <sys_created_on>2022-12-12 09:39:58</sys_created_on>
        <sys_id>7e35b6142f7bd1100c1058492799b686</sys_id>
        <sys_mod_count>0</sys_mod_count>
        <sys_name>Age</sys_name>
        <sys_package display_value="Hotel Reservation System" source="x_881199_hotel_res">2171b6dc2f3bd1100c1058492799b6f5</sys_package>
        <sys_policy/>
        <sys_scope display_value="Hotel Reservation System">2171b6dc2f3bd1100c1058492799b6f5</sys_scope>
        <sys_update_name>sys_dictionary_x_881199_hotel_res_hrs_user_profile_age</sys_update_name>
        <sys_updated_by>miguel.b</sys_updated_by>
        <sys_updated_on>2022-12-12 09:39:58</sys_updated_on>
        <table_reference>false</table_reference>
        <text_index>false</text_index>
        <unique>false</unique>
        <use_dependent_field>false</use_dependent_field>
        <use_dynamic_default>false</use_dynamic_default>
        <use_reference_qualifier>simple</use_reference_qualifier>
        <virtual>false</virtual>
        <widget/>
        <write_roles/>
        <xml_view>false</xml_view>
    </sys_dictionary>
<sys_update_version action="INSERT_OR_UPDATE">
        <action>DELETE</action>
        <application display_value="Hotel Reservation System">2171b6dc2f3bd1100c1058492799b6f5</application>
        <file_path/>
        <instance_id>b6528d11db87d5140b9d21c40596192a</instance_id>
        <instance_name>dev143370</instance_name>
        <name>sys_dictionary_x_881199_hotel_res_hrs_user_profile_age</name>
        <payload><![CDATA[<?xml version="1.0" encoding="UTF-8"?><record_update>
    <sys_dictionary action="INSERT_OR_UPDATE" element="age" table="x_881199_hotel_res_hrs_user_profile">
        <active>true</active>
        <array>false</array>
        <array_denormalized>false</array_denormalized>
        <attributes/>
        <audit>false</audit>
        <calculation/>
        <choice>0</choice>
        <choice_field/>
        <choice_table/>
        <column_label>Age</column_label>
        <comments/>
        <create_roles/>
        <default_value/>
        <defaultsort/>
        <delete_roles/>
        <dependent/>
        <dependent_on_field/>
        <display>false</display>
        <dynamic_creation>false</dynamic_creation>
        <dynamic_creation_script/>
        <dynamic_default_value/>
        <dynamic_ref_qual/>
        <element>age</element>
        <element_reference>false</element_reference>
        <foreign_database/>
        <function_definition/>
        <function_field>false</function_field>
        <internal_type display_value="Integer">integer</internal_type>
        <mandatory>false</mandatory>
        <max_length>40</max_length>
        <name>x_881199_hotel_res_hrs_user_profile</name>
        <next_element/>
        <primary>false</primary>
        <read_only>false</read_only>
        <read_roles/>
        <reference/>
        <reference_cascade_rule/>
        <reference_floats>false</reference_floats>
        <reference_key/>
        <reference_qual/>
        <reference_qual_condition/>
        <reference_type/>
        <sizeclass/>
        <spell_check>false</spell_check>
        <staged>false</staged>
        <sys_class_name>sys_dictionary</sys_class_name>
        <sys_created_by>miguel.b</sys_created_by>
        <sys_created_on>2022-12-12 09:39:58</sys_created_on>
        <sys_id>7e35b6142f7bd1100c1058492799b686</sys_id>
        <sys_mod_count>0</sys_mod_count>
        <sys_name>Age</sys_name>
        <sys_package display_value="Hotel Reservation System" source="x_881199_hotel_res">2171b6dc2f3bd1100c1058492799b6f5</sys_package>
        <sys_policy/>
        <sys_scope display_value="Hotel Reservation System">2171b6dc2f3bd1100c1058492799b6f5</sys_scope>
        <sys_update_name>sys_dictionary_x_881199_hotel_res_hrs_user_profile_age</sys_update_name>
        <sys_updated_by>miguel.b</sys_updated_by>
        <sys_updated_on>2022-12-12 09:39:58</sys_updated_on>
        <table_reference>false</table_reference>
        <text_index>false</text_index>
        <unique>false</unique>
        <use_dependent_field>false</use_dependent_field>
        <use_dynamic_default>false</use_dynamic_default>
        <use_reference_qualifier>simple</use_reference_qualifier>
        <virtual>false</virtual>
        <widget/>
        <write_roles/>
        <xml_view>false</xml_view>
    </sys_dictionary>
</record_update>]]></payload>
        <payload_hash>-328170614</payload_hash>
        <record_name>HRS Accounts.Age</record_name>
        <reverted_from/>
        <source>d80c5fe22ff311100c1058492799b63c</source>
        <source_table>sys_upgrade_history</source_table>
        <state>previous</state>
        <sys_created_by>admin</sys_created_by>
        <sys_created_on>2022-12-19 12:16:28</sys_created_on>
        <sys_id>af2cd7262ff311100c1058492799b68d</sys_id>
        <sys_mod_count>0</sys_mod_count>
        <sys_recorded_at>1852a505ed00000001</sys_recorded_at>
        <sys_updated_by>admin</sys_updated_by>
        <sys_updated_on>2022-12-19 12:16:28</sys_updated_on>
        <type>Dictionary</type>
        <update_guid>eb2cd726c7f31110abc139d5606cb38d</update_guid>
        <update_guid_history>eb2cd726c7f31110abc139d5606cb38d:0,431aa512017f51105576c0c34ce46197:508349174,c735b614d77bd11058fd64a63ff130c2:-1435123975</update_guid_history>
    </sys_update_version>
    <sys_metadata_delete action="INSERT_OR_UPDATE">
        <sys_audit_delete/>
        <sys_class_name>sys_metadata_delete</sys_class_name>
        <sys_created_by>admin</sys_created_by>
        <sys_created_on>2022-12-19 12:18:17</sys_created_on>
        <sys_db_object display_value="" name="sys_dictionary">sys_dictionary</sys_db_object>
        <sys_id>04ebadca535242f481b808cf055b5c10</sys_id>
        <sys_metadata>652c57262ff311100c1058492799b634</sys_metadata>
        <sys_mod_count>0</sys_mod_count>
        <sys_name>Age</sys_name>
        <sys_package display_value="Hotel Reservation System" source="x_881199_hotel_res">2171b6dc2f3bd1100c1058492799b6f5</sys_package>
        <sys_parent/>
        <sys_policy/>
        <sys_scope display_value="Hotel Reservation System">2171b6dc2f3bd1100c1058492799b6f5</sys_scope>
        <sys_scope_delete display_value="">335afa01cd914795ac3cfc5babd8d0e1</sys_scope_delete>
        <sys_update_name>sys_dictionary_x_881199_hotel_res_hrs_user_profile_age</sys_update_name>
        <sys_update_version display_value="sys_dictionary_x_881199_hotel_res_hrs_user_profile_age">af2cd7262ff311100c1058492799b68d</sys_update_version>
        <sys_updated_by>admin</sys_updated_by>
        <sys_updated_on>2022-12-19 12:18:17</sys_updated_on>
    </sys_metadata_delete>
</record_update>
